{
  "name": "그라밋",
  "title": "그라밋",
  "thumbnail": "/assets/project/25_thumbnail_gradmeet.png",
  "content": [
    "/assets/project/25_content_gradmeet_1.png",
    "/assets/project/25_content_gradmeet_2.png",
    "/assets/project/25_content_gradmeet_3.png"
  ],
  "tags": ["25기", "Web"],
  "team": [
    "김원지",
    "김현지",
    "정희경",
    "강지윤",
    "박규한",
    "임지수",
    "신수정"
  ],
  "field": ["Web"],
  "generation": 25,
  "program": [
    "TypeScript",
    "Next.js",
    "Tanstack Query",
    "react-hook-form",
    "zod",
    "radix-ui",
    "Kotlin",
    "Spring Boot 3.4.1",
    "Gradle",
    "Spring Security",
    "JSON Web Tokens",
    "Spring Data JPA",
    "Querydsl",
    "MariaDB",
    "Nginx",
    "Docker",
    "Redis",
    "AWS (EC2, RDS, S3, Lambda, SES)",
    "Github Action"
  ],
  "retrospects": [
    {
      "name": "김원지",
      "field": "PM",
      "content": "YAPP에서 해 보고 싶었던 것들이 많았는데, 활동하면서 결과에 상관없이 다양한 시도를 해 볼 수 있었던 것 같아서 뿌듯합니다. 얍 이전과 이후의 나... 조금 다를지도...? 여러 가지를 고민하고 결정하고 배워가는 소중한 시간이었어요. 무엇보다 좋은 팀원들과 함께 서비스를 만들어 나갈 수 있어서 정말 행운이었어요. 소중한 경험을 하게 해 준 YAPP에게도 감사합니다. 여기까지 제 회고를 읽으셨다면... 그라밋을 한번 사용해 보시는 건 어떨까요? 그라밋이 무럭무럭 자라길~ 🌱"
    },
    {
      "name": "김현지",
      "field": "Design",
      "content": "이렇게 좋은 팀원들과 함께 [그라밋] 이라는 멋진 프로젝트를 진행할 수 있어서 정말 행복한 순간들이었습니다! 앞으로도 소중한 인연과 함께,, 소중한 프로젝트를,, 더 꽉찬 경험으로 만들어 나아가고 싶습니다! 아좌좌 도비의 양말들~!🧦"
    },
    {
      "name": "정희경",
      "field": "Design",
      "content": "정말 많은 것을 배우고 갑니다! 좋은 사람들과 함께한 재미있는 프로젝트들… 4개월이 그야말로 생산적이고 행복한 시간이었습니다. 그라밋이 오래오래 지속되길 바랍니다!"
    },
    {
      "name": "강지윤",
      "field": "Web",
      "content": "YAPP 활동을 통해 많은 동기부여와 에너지를 얻을 수 있었습니다. 특히 그라밋을 만날 수 있어서 좋았어요. 믿고 의지할 수 있는 팀원들과 협업하면서 즐겁게 작업했습니다. YAPP은 끝나지만 그라밋은 계속된다✌✌️"
    },
    {
      "name": "박규한",
      "field": "Web",
      "content": "이번 동아리 활동을 통해 PM, 디자이너, 백엔드 개발자와 협력하여 하나의 서비스를 만들어나가는 소중한 경험을 하였습니다. 처음에는 각자 맡은 역할이 명확하게 나뉘어 있었지만, 진행하면서 서로의 업무에 대한 이해와 소통이 아주 중요하다는 것을 느꼈습니다.<br /><br /> 특히, 많은 것들을 개발 시작하기 전에 정했다고 생각했지만, 개발을 하면서 명확한 기준이나 디자인의 의도를 물어볼 수 밖에 없었습니다. 그렇게 계속 물어보는 과정이 처음에는 어려웠지만, 세부적인 부분들을 맞춰나가고 서로의 생각을 온전히 전달하면서 문제를 함께 해결해나가는 과정이 즐거웠습니다 😁 앞으로도 솔직하고 편하게 소통하며 더 나은 서비스를 만들어가고 싶습니다!!!"
    },

    {
      "name": "임지수",
      "field": "Server",
      "content": "4개월이라는 짧은 기간 동안 열정적인 팀원들과 함께 좋은 프로덕트를 만들어서 정말 좋았습니다! 함께 몰입했던 25기 야뿌들과 운영진 분들, 모두 고생 많으셨습니다. 🍀"
    },
    {
      "name": "신수정",
      "field": "Server",
      "content": "좋사좋시~ 그자체였던 얍과 그라밋!🥳 좋은 인연도 잔뜩 만들고, 개발적으로도 많은 성장을 이뤄낸 지난 4개월이었습니다! 돌이켜보면 성장 뿐만 아니라 개발을 즐기는 법을 알게 된 것 같아 소중한 경험이었어요! ㅎㅎ"
    }
  ],
  "webLink": "https://gradmeet.co.kr/",
  "description": "그라밋은 대학원 연구를 돕는 실험 참여자 모집 플랫폼이에요! <br /><br />🔬 연구자 <br />연구 참여자 모집이 어렵다면? <br />그라밋에 공고를 등록하면 모집 대상에게 자동으로 메일이 발송돼요.<br /><br />💰 참여자 <br />가까운 실험에 참여해 용돈을 벌고 싶다면?<br />내 조건에 맞는 실험만 모아보고 메일로 추천받으세요."
}
